redmineflow/__init__.py
redmineflow/cli.py
redmineflow/redmine.py
redmineflow/docs/__init__.py
redmineflow/docs/commands.py
redmineflow/file/__init__.py
redmineflow/file/commands.py
redmineflow/issues/__init__.py
redmineflow/issues/commands.py
redmineflow/wiki/__init__.py
redmineflow/wiki/commands.py
redmine_flow-0.4.7.dist-info/COPYING
redmine_flow-0.4.7.dist-info/METADATA
redmine_flow-0.4.7.dist-info/WHEEL
redmine_flow-0.4.7.dist-info/entry_points.txt
redmine_flow-0.4.7.dist-info/top_level.txt
redmine_flow-0.4.7.dist-info/RECORD
